{
  "registry_version": 171,
  "updated": "2026-05-24",
  "manager": {
    "id": "nymphscore-manager",
    "name": "NymphsCore Manager",
    "manifest_version": "0.9.48",
    "artifact_url": "https://raw.githubusercontent.com/nymphnerds/NymphsCore/9de0ebe64d891a2beb649c13abd5ba778534f432/Manager/apps/NymphsCoreManager/publish/NymphsCoreManager-win-x64.zip",
    "artifact_hash": "f2d64791c88f3ee8054dd8a853e5f4589b7991066238eb9652fc9b1b89fc8901",
    "source_url": "https://github.com/nymphnerds/NymphsCore"
  },
  "modules": [
    {
      "id": "worbi",
      "name": "WORBI",
      "short_name": "WB",
      "category": "tool",
      "packaging": "archive",
      "summary": "Local-first worldbuilding workspace for lore, characters, locations, timelines, notes, and project planning.",
      "overview": {
        "body": "WORBI is a browser-based worldbuilding tool packaged as a Nymph module. It is designed for writers, game developers, solo creators, and teams who need a local project bible for fictional worlds and production notes. WORBI 6.3.24 provisions its local Node.js runtime during Install/Update and starts from that installed runtime path, so Start does not need a user-managed node command on PATH.",
        "works_with": [
          "Standalone browser workflow",
          "NymphsCore Manager",
          "Game writing and planning workflows",
          "Blender/Unity/Unreal projects as external reference material"
        ],
        "requirements": [
          "NymphsCore base WSL runtime",
          "Nymphs Brain local AI stack",
          "Local WebView2 or browser access to the WORBI web app"
        ],
        "links": [
          {
            "label": "WORBI module source",
            "url": "https://github.com/nymphnerds/worbi"
          }
        ]
      },
      "install_root": "$HOME/worbi",
      "sort_order": 50,
      "channel": "test",
      "trusted": true,
      "manifest_url": "https://raw.githubusercontent.com/nymphnerds/worbi/main/nymph.json",
      "manifest_version": "6.3.24",
      "manifest_hash": "31f8cc2da3009261d5483450212271d9a7e00c87530c1c96453592c170e234c0"
    },
    {
      "id": "zimage",
      "name": "Nymphs Image",
      "short_name": "NI",
      "category": "image",
      "kind": "image",
      "packaging": "repo",
      "summary": "Nymphs Image frontend for local Z-Image Turbo, Gemini Flash image generation, and part extraction.",
      "install_root": "$HOME/Z-Image",
      "sort_order": 20,
      "channel": "test",
      "trusted": true,
      "manifest_url": "https://raw.githubusercontent.com/nymphnerds/zimage/main/nymph.json",
      "manifest_version": "0.1.54",
      "manifest_hash": "02aa5e0c9f3acc54d07564bdb71d1277751af9d947ea1a47772c8866fa41ae09"
    },
    {
      "id": "trellis",
      "name": "TRELLIS.2",
      "short_name": "TR",
      "category": "3d",
      "packaging": "repo",
      "summary": "Local TRELLIS.2 GGUF 3D backend with shared Pixal3D-ready runtime, model fetch, and smoke-test hooks.",
      "install_root": "$HOME/TRELLIS.2",
      "sort_order": 40,
      "channel": "test",
      "trusted": true,
      "manifest_url": "https://raw.githubusercontent.com/nymphnerds/trellis/main/nymph.json",
      "manifest_version": "0.1.35",
      "manifest_hash": "e7a5a8b8f445c71616c4be93acce0322860ec3e7538007433dc8f93e535ddfec"
    },
    {
      "id": "pixal3d",
      "name": "Pixal3D",
      "short_name": "PX",
      "category": "3d",
      "packaging": "repo",
      "summary": "Pixal3D generates high-fidelity textured 3D assets from a single image.",
      "overview": {
        "body": "Install sets up the local Pixal3D runtime. The install options below are for building FlashAttention during setup. Auto-detect is recommended. If the build runs out of memory, retry with lower Max jobs or NVCC threads.\n\nFetch Models downloads the Pixal3D checkpoints and helper models. Before Fetch Models, fill the BRIA RMBG-2.0 form with the same Hugging Face account used for your token.",
        "requirements": [],
        "links": [
          {
            "label": "Fill BRIA form",
            "url": "https://huggingface.co/briaai/RMBG-2.0"
          },
          {
            "label": "Pixal3D models",
            "url": "https://huggingface.co/TencentARC/Pixal3D"
          },
          {
            "label": "Pixal3D source",
            "url": "https://github.com/TencentARC/Pixal3D"
          },
          {
            "label": "Pixal3D MIT license",
            "url": "https://github.com/TencentARC/Pixal3D/blob/master/LICENSE"
          }
        ]
      },
      "install_root": "$HOME/Pixal3D",
      "sort_order": 45,
      "channel": "test",
      "trusted": true,
      "manifest_url": "https://raw.githubusercontent.com/nymphnerds/Pixal3D/master/nymph.json",
      "manifest_version": "0.1.109",
      "manifest_hash": "ba63a34d3ee331754f4616e32c8856976a2ba52122f8d042b90f9937c888f945"
    },
    {
      "id": "brain",
      "name": "Brain",
      "short_name": "BR",
      "category": "service",
      "packaging": "repo",
      "summary": "Local assistant, llama-server, Open WebUI, and MCP orchestration stack.",
      "install_root": "$HOME/Nymphs-Brain",
      "sort_order": 10,
      "channel": "test",
      "trusted": true,
      "manifest_url": "https://raw.githubusercontent.com/nymphnerds/brain/main/nymph.json",
      "manifest_version": "0.1.10",
      "manifest_hash": "8e4f27e5fa05fd6f2287dbd5e2b2c87fa753f581d81c3cd3b7b4340c64acc64c"
    },
    {
      "id": "lora",
      "name": "LoRA",
      "short_name": "LO",
      "category": "training",
      "packaging": "repo",
      "summary": "AI Toolkit powered Z-Image Turbo LoRA training sidecar for datasets, jobs, and generated adapters.",
      "install_root": "$HOME/LoRA",
      "sort_order": 30,
      "channel": "test",
      "trusted": true,
      "manifest_url": "https://raw.githubusercontent.com/nymphnerds/lora/main/nymph.json",
      "manifest_version": "0.1.43",
      "manifest_hash": "be7f1b4385851bd416a4747439f7fbdd347ab2c8b03ebf57db6d5a139ed7af42"
    }
  ]
}
